sunw_mcp_seniverse_weather/__init__.py
sunw_mcp_seniverse_weather/__main__.py
sunw_mcp_seniverse_weather/server.py
sunw_mcp_seniverse_weather-0.0.99.dist-info/METADATA
sunw_mcp_seniverse_weather-0.0.99.dist-info/WHEEL
sunw_mcp_seniverse_weather-0.0.99.dist-info/entry_points.txt
sunw_mcp_seniverse_weather-0.0.99.dist-info/RECORD
